action_collective/__init__.py
action_collective/client.py
action_collective/models/actions.py
action_collective/models/requests.py
action_collective/services/backend.py
action_collective/services/llm.py
action_collective-0.0.4.dist-info/METADATA
action_collective-0.0.4.dist-info/WHEEL
action_collective-0.0.4.dist-info/RECORD
