Metadata-Version: 2.1
Name: action-collective
Version: 0.0.4
Summary: A framework for dynamic action generation and reuse with LLMs
Home-page: https://github.com/CakeCrusher/ActionCollective
License: MIT
Keywords: llm,ai,actions,tools
Author: Sebastian Sosa
Author-email: 1sebastian1sosa1@gmail.com
Requires-Python: >=3.9,<4.0
Classifier: License :: OSI Approved :: MIT License
Classifier: Programming Language :: Python :: 3
Classifier: Programming Language :: Python :: 3.9
Classifier: Programming Language :: Python :: 3.10
Classifier: Programming Language :: Python :: 3.11
Classifier: Programming Language :: Python :: 3.12
Classifier: Programming Language :: Python :: 3.13
Requires-Dist: numpy (>=1.24.0,<2.0.0)
Requires-Dist: openai (>=1.57.4,<2.0.0)
Requires-Dist: pydantic (>=2.5.1,<3.0.0)
Requires-Dist: python-dotenv (>=1.0.0,<2.0.0)
Requires-Dist: requests (>=2.31.0,<3.0.0)
Project-URL: Documentation, https://github.com/CakeCrusher/ActionCollective
Project-URL: Repository, https://github.com/CakeCrusher/ActionCollective
